{
  "parent": "minecraft:recipes/root",
  "rewards": {
    "recipes": [
      "twilightforest:compressed_blocks/reversed/fiery_block_to_ingot"
    ]
  },
  "criteria": {
    "has_item": {
      "trigger": "minecraft:inventory_changed",
      "conditions": {
        "items": [
          {
            "tag": "forge:storage_blocks/fiery"
          }
        ]
      }
    },
    "has_the_recipe": {
      "trigger": "minecraft:recipe_unlocked",
      "conditions": {
        "recipe": "twilightforest:compressed_blocks/reversed/fiery_block_to_ingot"
      }
    }
  },
  "requirements": [
    [
      "has_item",
      "has_the_recipe"
    ]
  ]
}