{
  "scale": 0.1,
  "effects": {
    "mood_sound": {
      "sound": "minecraft:ambient.cave",
      "tick_delay": 6000,
      "block_search_extent": 8,
      "offset": 2.0
    },
    "sky_color": 2105930,
    "fog_color": 12648408,
    "water_color": 4159204,
    "water_fog_color": 329011
  },
  "surface_builder": {
    "config": {
      "top_material": {
        "Properties": {
          "snowy": "false"
        },
        "Name": "minecraft:grass_block"
      },
      "under_material": {
        "Name": "minecraft:dirt"
      },
      "underwater_material": {
        "Name": "minecraft:gravel"
      }
    },
    "type": "minecraft:default"
  },
  "carvers": {},
  "features": [
    [],
    [],
    [],
    [],
    [],
    [],
    [
      {
        "config": {
          "feature": {
            "config": {
              "feature": {
                "config": {
                  "feature": {
                    "config": {
                      "target": {
                        "tag": "minecraft:base_stone_overworld",
                        "predicate_type": "minecraft:tag_match"
                      },
                      "state": {
                        "Name": "minecraft:dirt"
                      },
                      "size": 33
                    },
                    "type": "minecraft:ore"
                  },
                  "decorator": {
                    "config": {
                      "bottom_offset": 0,
                      "top_offset": 0,
                      "maximum": 256
                    },
                    "type": "minecraft:range"
                  }
                },
                "type": "minecraft:decorated"
              },
              "decorator": {
                "config": {},
                "type": "minecraft:square"
              }
            },
            "type": "minecraft:decorated"
          },
          "decorator": {
            "config": {
              "count": 10
            },
            "type": "minecraft:count"
          }
        },
        "type": "minecraft:decorated"
      },
      {
        "config": {
          "feature": {
            "config": {
              "feature": {
                "config": {
                  "feature": {
                    "config": {
                      "target": {
                        "tag": "minecraft:base_stone_overworld",
                        "predicate_type": "minecraft:tag_match"
                      },
                      "state": {
                        "Name": "minecraft:gravel"
                      },
                      "size": 33
                    },
                    "type": "minecraft:ore"
                  },
                  "decorator": {
                    "config": {
                      "bottom_offset": 0,
                      "top_offset": 0,
                      "maximum": 256
                    },
                    "type": "minecraft:range"
                  }
                },
                "type": "minecraft:decorated"
              },
              "decorator": {
                "config": {},
                "type": "minecraft:square"
              }
            },
            "type": "minecraft:decorated"
          },
          "decorator": {
            "config": {
              "count": 8
            },
            "type": "minecraft:count"
          }
        },
        "type": "minecraft:decorated"
      },
      {
        "config": {
          "feature": {
            "config": {
              "feature": {
                "config": {
                  "feature": {
                    "config": {
                      "target": {
                        "tag": "minecraft:base_stone_overworld",
                        "predicate_type": "minecraft:tag_match"
                      },
                      "state": {
                        "Name": "minecraft:granite"
                      },
                      "size": 33
                    },
                    "type": "minecraft:ore"
                  },
                  "decorator": {
                    "config": {
                      "bottom_offset": 0,
                      "top_offset": 0,
                      "maximum": 80
                    },
                    "type": "minecraft:range"
                  }
                },
                "type": "minecraft:decorated"
              },
              "decorator": {
                "config": {},
                "type": "minecraft:square"
              }
            },
            "type": "minecraft:decorated"
          },
          "decorator": {
            "config": {
              "count": 10
            },
            "type": "minecraft:count"
          }
        },
        "type": "minecraft:decorated"
      },
      {
        "config": {
          "feature": {
            "config": {
              "feature": {
                "config": {
                  "feature": {
                    "config": {
                      "target": {
                        "tag": "minecraft:base_stone_overworld",
                        "predicate_type": "minecraft:tag_match"
                      },
                      "state": {
                        "Name": "minecraft:diorite"
                      },
                      "size": 33
                    },
                    "type": "minecraft:ore"
                  },
                  "decorator": {
                    "config": {
                      "bottom_offset": 0,
                      "top_offset": 0,
                      "maximum": 80
                    },
                    "type": "minecraft:range"
                  }
                },
                "type": "minecraft:decorated"
              },
              "decorator": {
                "config": {},
                "type": "minecraft:square"
              }
            },
            "type": "minecraft:decorated"
          },
          "decorator": {
            "config": {
              "count": 10
            },
            "type": "minecraft:count"
          }
        },
        "type": "minecraft:decorated"
      },
      {
        "config": {
          "feature": {
            "config": {
              "feature": {
                "config": {
                  "feature": {
                    "config": {
                      "target": {
                        "tag": "minecraft:base_stone_overworld",
                        "predicate_type": "minecraft:tag_match"
                      },
                      "state": {
                        "Name": "minecraft:andesite"
                      },
                      "size": 33
                    },
                    "type": "minecraft:ore"
                  },
                  "decorator": {
                    "config": {
                      "bottom_offset": 0,
                      "top_offset": 0,
                      "maximum": 80
                    },
                    "type": "minecraft:range"
                  }
                },
                "type": "minecraft:decorated"
              },
              "decorator": {
                "config": {},
                "type": "minecraft:square"
              }
            },
            "type": "minecraft:decorated"
          },
          "decorator": {
            "config": {
              "count": 10
            },
            "type": "minecraft:count"
          }
        },
        "type": "minecraft:decorated"
      },
      {
        "config": {
          "feature": {
            "config": {
              "feature": {
                "config": {
                  "feature": {
                    "config": {
                      "target": {
                        "tag": "minecraft:base_stone_overworld",
                        "predicate_type": "minecraft:tag_match"
                      },
                      "state": {
                        "Name": "minecraft:coal_ore"
                      },
                      "size": 17
                    },
                    "type": "minecraft:ore"
                  },
                  "decorator": {
                    "config": {
                      "bottom_offset": 0,
                      "top_offset": 0,
                      "maximum": 128
                    },
                    "type": "minecraft:range"
                  }
                },
                "type": "minecraft:decorated"
              },
              "decorator": {
                "config": {},
                "type": "minecraft:square"
              }
            },
            "type": "minecraft:decorated"
          },
          "decorator": {
            "config": {
              "count": 20
            },
            "type": "minecraft:count"
          }
        },
        "type": "minecraft:decorated"
      },
      {
        "config": {
          "feature": {
            "config": {
              "feature": {
                "config": {
                  "feature": {
                    "config": {
                      "target": {
                        "tag": "minecraft:base_stone_overworld",
                        "predicate_type": "minecraft:tag_match"
                      },
                      "state": {
                        "Name": "minecraft:iron_ore"
                      },
                      "size": 9
                    },
                    "type": "minecraft:ore"
                  },
                  "decorator": {
                    "config": {
                      "bottom_offset": 0,
                      "top_offset": 0,
                      "maximum": 64
                    },
                    "type": "minecraft:range"
                  }
                },
                "type": "minecraft:decorated"
              },
              "decorator": {
                "config": {},
                "type": "minecraft:square"
              }
            },
            "type": "minecraft:decorated"
          },
          "decorator": {
            "config": {
              "count": 20
            },
            "type": "minecraft:count"
          }
        },
        "type": "minecraft:decorated"
      },
      {
        "config": {
          "feature": {
            "config": {
              "feature": {
                "config": {
                  "feature": {
                    "config": {
                      "target": {
                        "tag": "minecraft:base_stone_overworld",
                        "predicate_type": "minecraft:tag_match"
                      },
                      "state": {
                        "Name": "minecraft:gold_ore"
                      },
                      "size": 9
                    },
                    "type": "minecraft:ore"
                  },
                  "decorator": {
                    "config": {
                      "bottom_offset": 0,
                      "top_offset": 0,
                      "maximum": 32
                    },
                    "type": "minecraft:range"
                  }
                },
                "type": "minecraft:decorated"
              },
              "decorator": {
                "config": {},
                "type": "minecraft:square"
              }
            },
            "type": "minecraft:decorated"
          },
          "decorator": {
            "config": {
              "count": 2
            },
            "type": "minecraft:count"
          }
        },
        "type": "minecraft:decorated"
      },
      {
        "config": {
          "feature": {
            "config": {
              "feature": {
                "config": {
                  "feature": {
                    "config": {
                      "target": {
                        "tag": "minecraft:base_stone_overworld",
                        "predicate_type": "minecraft:tag_match"
                      },
                      "state": {
                        "Properties": {
                          "lit": "false"
                        },
                        "Name": "minecraft:redstone_ore"
                      },
                      "size": 8
                    },
                    "type": "minecraft:ore"
                  },
                  "decorator": {
                    "config": {
                      "bottom_offset": 0,
                      "top_offset": 0,
                      "maximum": 16
                    },
                    "type": "minecraft:range"
                  }
                },
                "type": "minecraft:decorated"
              },
              "decorator": {
                "config": {},
                "type": "minecraft:square"
              }
            },
            "type": "minecraft:decorated"
          },
          "decorator": {
            "config": {
              "count": 8
            },
            "type": "minecraft:count"
          }
        },
        "type": "minecraft:decorated"
      },
      {
        "config": {
          "feature": {
            "config": {
              "feature": {
                "config": {
                  "target": {
                    "tag": "minecraft:base_stone_overworld",
                    "predicate_type": "minecraft:tag_match"
                  },
                  "state": {
                    "Name": "minecraft:diamond_ore"
                  },
                  "size": 8
                },
                "type": "minecraft:ore"
              },
              "decorator": {
                "config": {
                  "bottom_offset": 0,
                  "top_offset": 0,
                  "maximum": 16
                },
                "type": "minecraft:range"
              }
            },
            "type": "minecraft:decorated"
          },
          "decorator": {
            "config": {},
            "type": "minecraft:square"
          }
        },
        "type": "minecraft:decorated"
      },
      {
        "config": {
          "feature": {
            "config": {
              "feature": {
                "config": {
                  "target": {
                    "tag": "minecraft:base_stone_overworld",
                    "predicate_type": "minecraft:tag_match"
                  },
                  "state": {
                    "Name": "minecraft:lapis_ore"
                  },
                  "size": 7
                },
                "type": "minecraft:ore"
              },
              "decorator": {
                "config": {
                  "baseline": 16,
                  "spread": 16
                },
                "type": "minecraft:depth_average"
              }
            },
            "type": "minecraft:decorated"
          },
          "decorator": {
            "config": {},
            "type": "minecraft:square"
          }
        },
        "type": "minecraft:decorated"
      }
    ]
  ],
  "starts": [],
  "spawners": {
    "monster": [],
    "creature": [],
    "ambient": [],
    "water_creature": [],
    "water_ambient": [],
    "misc": []
  },
  "spawn_costs": {},
  "player_spawn_friendly": false,
  "precipitation": "rain",
  "temperature": 0.3,
  "downfall": 0.2,
  "category": "none",
  "depth": 6.0
}