{
  "parent": "minecraft:block/block",
  "ambientocclusion": false,
  "elements": [
    {
      "faces": {
        "east": {
          "emissivity": 15,
          "texture": "#pane",
          "uv": [
            9.0,
            9.0,
            16.0,
            16.0
          ]
        },
        "north": {
          "cullface": "north",
          "emissivity": 15,
          "texture": "#pane",
          "uv": [
            7.0,
            9.0,
            9.0,
            16.0
          ]
        },
        "up": {
          "cullface": "up",
          "emissivity": 15,
          "texture": "#pane"
        },
        "west": {
          "emissivity": 15,
          "texture": "#pane",
          "uv": [
            0.0,
            9.0,
            7.0,
            16.0
          ]
        }
      },
      "from": [
        7,
        9,
        0
      ],
      "shade": false,
      "to": [
        9,
        16,
        7
      ]
    }
  ],
  "textures": {
    "particle": "#pane"
  }
}