{
  "type": "twilightforest:final_castle",
  "adjust_structure_elevation": false,
  "advancements_required": [
    "twilightforest:progress_troll"
  ],
  "allow_biome_surface_decorations": false,
  "allow_biome_underground_decorations": true,
  "ambient_spawns": [],
  "biomes": "#twilightforest:valid_final_castle_biomes",
  "chunk_clearance_radius": 4,
  "hint_item": {
    "Count": 1,
    "id": "minecraft:written_book",
    "tag": {
      "author": "twilightforest.book.author",
      "generation": 3,
      "pages": [
        "{\"translate\":\"twilightforest.book.unknown.1\"}",
        "{\"translate\":\"twilightforest.book.unknown.2\"}"
      ],
      "title": "twilightforest.book.unknown",
      "twilightforest:book": 1
    }
  },
  "hint_mob": "twilightforest:kobold",
  "labelled_monster_spawns": {
    "0": [],
    "1": [],
    "2": [],
    "3": []
  },
  "spawn_overrides": {
    "ambient": {
      "bounding_box": "full",
      "spawns": []
    },
    "axolotls": {
      "bounding_box": "full",
      "spawns": []
    },
    "creature": {
      "bounding_box": "full",
      "spawns": []
    },
    "misc": {
      "bounding_box": "full",
      "spawns": []
    },
    "monster": {
      "bounding_box": "full",
      "spawns": []
    },
    "underground_water_creature": {
      "bounding_box": "full",
      "spawns": []
    },
    "water_ambient": {
      "bounding_box": "full",
      "spawns": []
    },
    "water_creature": {
      "bounding_box": "full",
      "spawns": []
    }
  },
  "step": "surface_structures",
  "terrain_adaptation": "beard_thin",
  "water_spawns": []
}