{
  "parent": "twilightforest:progress_lich",
  "criteria": {
    "hydra": {
      "conditions": {
        "player": [
          {
            "condition": "minecraft:entity_properties",
            "entity": "this",
            "predicate": {
              "type_specific": {
                "type": "player",
                "advancements": {
                  "twilightforest:progress_hydra": true
                }
              }
            }
          }
        ]
      },
      "trigger": "minecraft:tick"
    },
    "snow_queen": {
      "conditions": {
        "player": [
          {
            "condition": "minecraft:entity_properties",
            "entity": "this",
            "predicate": {
              "type_specific": {
                "type": "player",
                "advancements": {
                  "twilightforest:progress_glacier": true
                }
              }
            }
          }
        ]
      },
      "trigger": "minecraft:tick"
    },
    "ur_ghast": {
      "conditions": {
        "player": [
          {
            "condition": "minecraft:entity_properties",
            "entity": "this",
            "predicate": {
              "type_specific": {
                "type": "player",
                "advancements": {
                  "twilightforest:progress_ur_ghast": true
                }
              }
            }
          }
        ]
      },
      "trigger": "minecraft:tick"
    }
  },
  "display": {
    "announce_to_chat": true,
    "description": {
      "translate": "advancement.twilightforest.progress_merge.desc",
      "with": [
        {
          "translate": "entity.twilightforest.hydra"
        },
        {
          "translate": "entity.twilightforest.ur_ghast"
        },
        {
          "translate": "entity.twilightforest.snow_queen"
        }
      ]
    },
    "frame": "goal",
    "hidden": false,
    "icon": {
      "item": "twilightforest:uberous_soil"
    },
    "show_toast": true,
    "title": {
      "translate": "advancement.twilightforest.progress_merge"
    }
  },
  "requirements": [
    [
      "hydra"
    ],
    [
      "ur_ghast"
    ],
    [
      "snow_queen"
    ]
  ]
}