{
  "display": {
    "icon": {
      "item": "minecraft:iron_boots"
    },
    "title": {
      "translate": "advancement.twilightHill1"
    },
    "description": {
      "translate": "advancement.twilightHill1.desc"
    }
  },
  "parent": "twilightforest:twilight_arrival",
  "__comment": "These are triggered by code in order to test for a Hill nearby. In the future, these may become data-driven",
  "criteria": {
    "boggard": {
      "trigger": "minecraft:impossible"
    },
    "redcap": {
      "trigger": "minecraft:impossible"
    }
  },
  "requirements": [
    [ "boggard", "redcap" ]
  ]
}
