{
  "config": {
    "feature": {
      "config": {
        "feature": {
          "config": {
            "feature": {
              "config": {
                "feature": {
                  "config": {},
                  "type": "twilightforest:monolith"
                },
                "decorator": {
                  "config": {
                    "occupies_surface": true,
                    "occupies_underground": false
                  },
                  "type": "twilightforest:no_structure"
                }
              },
              "type": "minecraft:decorated"
            },
            "decorator": {
              "config": {
                "heightmap": "WORLD_SURFACE_WG"
              },
              "type": "minecraft:heightmap"
            }
          },
          "type": "minecraft:decorated"
        },
        "decorator": {
          "config": {},
          "type": "minecraft:square"
        }
      },
      "type": "minecraft:decorated"
    },
    "decorator": {
      "config": {
        "chance": 90
      },
      "type": "minecraft:chance"
    }
  },
  "type": "minecraft:decorated"
}