{
  "criteria": {
    "ingredient": { "trigger": "minecraft:inventory_changed", "conditions": { "items": [{ "item": "twilightforest:ironwood_raw"     }]}},
    "ingredien2": { "trigger": "minecraft:inventory_changed", "conditions": { "items": [{ "item": "twilightforest:ironwood_ingot"   }]}},
    "pickaxe"   : { "trigger": "minecraft:inventory_changed", "conditions": { "items": [{ "item": "twilightforest:ironwood_pickaxe" }]}},
    "sword"     : { "trigger": "minecraft:inventory_changed", "conditions": { "items": [{ "item": "twilightforest:ironwood_sword"   }]}},
    "axe"       : { "trigger": "minecraft:inventory_changed", "conditions": { "items": [{ "item": "twilightforest:ironwood_axe"     }]}},
    "shovel"    : { "trigger": "minecraft:inventory_changed", "conditions": { "items": [{ "item": "twilightforest:ironwood_shovel"  }]}},
    "hoe"       : { "trigger": "minecraft:inventory_changed", "conditions": { "items": [{ "item": "twilightforest:ironwood_hoe"     }]}}
  },
  "requirements": [
    [ "ingredient", "ingredien2", "pickaxe", "sword", "axe", "shovel", "hoe" ]
  ]
}